insta_checker.py
insta_checker-0.4.7.dist-info/LICENSE
insta_checker-0.4.7.dist-info/WHEEL
insta_checker-0.4.7.dist-info/METADATA
insta_checker-0.4.7.dist-info/RECORD
