Metadata-Version: 2.1
Name: insta-checker
Version: 0.4.7
Summary: Python Instagram API checker / scrapper / wrapper 2021. Fast and asynchronously scrapes instagram profiles and posts, powered by aiohttp.
Home-page: https://github.com/gh0st-work/insta_checker
License: MIT
Keywords: instagram,API,scrape,checker,scrapper
Author: Anton Nechaev
Author-email: antonnechaev990@gmail.com
Requires-Python: >=3.6,<4.0
Classifier: License :: OSI Approved :: MIT License
Classifier: Programming Language :: Python :: 3
Classifier: Programming Language :: Python :: 3.6
Classifier: Programming Language :: Python :: 3.7
Classifier: Programming Language :: Python :: 3.8
Classifier: Programming Language :: Python :: 3.9
Requires-Dist: aiohttp (>=3.7.4,<4.0.0)
Project-URL: Repository, https://github.com/gh0st-work/insta_checker
